setup.cfg
setup.py
KerasModelZoo.egg-info/PKG-INFO
KerasModelZoo.egg-info/SOURCES.txt
KerasModelZoo.egg-info/dependency_links.txt
KerasModelZoo.egg-info/requires.txt
KerasModelZoo.egg-info/top_level.txt
kerasmodelzoo/__init__.py
kerasmodelzoo/data/c3d_mean.npy
kerasmodelzoo/data/vgg_mean.npy