Metadata-Version: 1.1
Name: KerasModelZoo
Version: 0.0.1
Summary: A package with models for Keras
Home-page: UNKNOWN
Author: Alberto Montes
Author-email: alm59321@gmail.com
License: MIT
Download-URL: https://github.com/albertomontesg/kerasmodelzoo/tarball/0.0.1
Keywords: Keras,deeplearning,Theano,Tensorflow,models
Platform: UNKNOWN
